AUTHORS.rst
CHANGES.rst
CONTRIBUTING.rst
HISTORY.rst
LICENSE
MANIFEST.in
README.rst
setup.cfg
setup.py
docs/Makefile
docs/authors.rst
docs/conf.py
docs/contributing.rst
docs/history.rst
docs/index.rst
docs/installation.rst
docs/make.bat
docs/readme.rst
docs/usage.rst
rabird/__init__.py
rabird.qt.egg-info/PKG-INFO
rabird.qt.egg-info/SOURCES.txt
rabird.qt.egg-info/dependency_links.txt
rabird.qt.egg-info/entry_points.txt
rabird.qt.egg-info/namespace_packages.txt
rabird.qt.egg-info/not-zip-safe
rabird.qt.egg-info/requires.txt
rabird.qt.egg-info/top_level.txt
rabird/qt/__init__.py
rabird/qt/application.py
rabird/qt/commands.py
rabird/qt/eventlet.py
rabird/qt/singleworld.py
rabird/qt/utils.py
tests/__init__.py
tests/test_rabird_qt.py