Metadata-Version: 1.1
Name: rabird.qt
Version: 0.2.2
Summary: An extension library for Qt library
Home-page: https://github.com/starofrainnight/rabird.qt
Author: Hong-She Liang
Author-email: starofrainnight@gmail.com
License: Apache Software License
Keywords: rabird.qt
Platform: UNKNOWN
Classifier: Development Status :: 3 - Alpha
Classifier: Intended Audience :: Developers
Classifier: License :: OSI Approved :: Apache Software License
Classifier: Operating System :: OS Independent
Classifier: Programming Language :: Python :: 3
Classifier: Topic :: Software Development :: Libraries
